scs_core/__init__.py
scs_core/aqcsv/__init__.py
scs_core/aqcsv/conf/__init__.py
scs_core/aqcsv/conf/airnow_site_conf.py
scs_core/aqcsv/conf/airnow_uploader_conf.py
scs_core/aqcsv/connector/__init__.py
scs_core/aqcsv/connector/airnow_mapping_task.py
scs_core/aqcsv/connector/datum_mapping.py
scs_core/aqcsv/connector/source_mapping.py
scs_core/aqcsv/connector/archive/source_mappings.csv
scs_core/aqcsv/data/__init__.py
scs_core/aqcsv/data/aqcsv_datetime.py
scs_core/aqcsv/data/aqcsv_record.py
scs_core/aqcsv/data/aqcsv_site.py
scs_core/aqcsv/specification/__init__.py
scs_core/aqcsv/specification/agency.py
scs_core/aqcsv/specification/country.py
scs_core/aqcsv/specification/country_iso.py
scs_core/aqcsv/specification/country_numeric.py
scs_core/aqcsv/specification/method.py
scs_core/aqcsv/specification/mpc.py
scs_core/aqcsv/specification/parameter.py
scs_core/aqcsv/specification/qc.py
scs_core/aqcsv/specification/qualifier.py
scs_core/aqcsv/specification/unit.py
scs_core/aqcsv/specification/archive/agencies.csv
scs_core/aqcsv/specification/archive/countries.csv
scs_core/aqcsv/specification/archive/methods.csv
scs_core/aqcsv/specification/archive/mpcs.csv
scs_core/aqcsv/specification/archive/parameters.csv
scs_core/aqcsv/specification/archive/qcs.csv
scs_core/aqcsv/specification/archive/qualifiers.csv
scs_core/aqcsv/specification/archive/units.csv
scs_core/aws/__init__.py
scs_core/aws/client/__init__.py
scs_core/aws/client/access_key.py
scs_core/aws/client/api_auth.py
scs_core/aws/client/api_client.py
scs_core/aws/client/api_intercourse.py
scs_core/aws/client/client.py
scs_core/aws/client/client_auth.py
scs_core/aws/client/device_control_client.py
scs_core/aws/client/email_client.py
scs_core/aws/client/monitor_auth.py
scs_core/aws/client/mqtt_client.py
scs_core/aws/client/rest_client.py
scs_core/aws/client_traffic/__init__.py
scs_core/aws/client_traffic/client_traffic.py
scs_core/aws/client_traffic/client_traffic_finder.py
scs_core-3.16.3.dist-info/LICENSE
scs_core-3.16.3.dist-info/METADATA
scs_core-3.16.3.dist-info/WHEEL
scs_core-3.16.3.dist-info/top_level.txt
scs_core-3.16.3.dist-info/RECORD
